scikit_gstat-1.0.23.dist-info/licenses/LICENSE
skgstat/DirectionalVariogram.py
skgstat/Kriging.py
skgstat/MetricSpace.py
skgstat/SpaceTimeVariogram.py
skgstat/Variogram.py
skgstat/__init__.py
skgstat/__version__.py
skgstat/binning.py
skgstat/estimators.py
skgstat/models.py
skgstat/stmodels.py
skgstat/data/__init__.py
skgstat/data/_loader.py
skgstat/data/rf/aniso.png
skgstat/data/rf/pancake.png
skgstat/data/samples/README.md
skgstat/data/samples/meuse.txt
skgstat/interfaces/__init__.py
skgstat/interfaces/gstools.py
skgstat/interfaces/pykrige.py
skgstat/interfaces/variogram_estimator.py
skgstat/plotting/__init__.py
skgstat/plotting/directtional_variogram.py
skgstat/plotting/stvariogram_marginal.py
skgstat/plotting/stvariogram_plot2d.py
skgstat/plotting/stvariogram_plot3d.py
skgstat/plotting/variogram_dd_plot.py
skgstat/plotting/variogram_location_trend.py
skgstat/plotting/variogram_plot.py
skgstat/plotting/variogram_scattergram.py
skgstat/tests/__init__.py
skgstat/tests/test_binning.py
skgstat/tests/test_cross_utility.py
skgstat/tests/test_data_loader.py
skgstat/tests/test_directionalvariogram.py
skgstat/tests/test_estimator.py
skgstat/tests/test_interfaces.py
skgstat/tests/test_isotropic.py
skgstat/tests/test_kriging.py
skgstat/tests/test_likelihood.py
skgstat/tests/test_metric_space.py
skgstat/tests/test_models.py
skgstat/tests/test_plotting_backend.py
skgstat/tests/test_spacetimevariogram.py
skgstat/tests/test_stmodels.py
skgstat/tests/test_util.py
skgstat/tests/test_variogram.py
skgstat/util/__init__.py
skgstat/util/cross_validation.py
skgstat/util/cross_variogram.py
skgstat/util/likelihood.py
skgstat/util/shannon.py
skgstat/util/uncertainty.py
scikit_gstat-1.0.23.dist-info/METADATA
scikit_gstat-1.0.23.dist-info/WHEEL
scikit_gstat-1.0.23.dist-info/top_level.txt
scikit_gstat-1.0.23.dist-info/RECORD
