Metadata-Version: 2.4
Name: scikit-gstat
Version: 1.0.23
Summary: Geostatistical expansion in the scipy style
Author: Mirko Maelicke
Author-email: mirko.maelicke@kit.edu
License: MIT License
Classifier: Development Status :: 5 - Production/Stable
Classifier: Intended Audience :: Science/Research
Classifier: License :: OSI Approved :: MIT License
Classifier: Natural Language :: English
Classifier: Programming Language :: Python :: 3.9
Classifier: Programming Language :: Python :: 3.10
Classifier: Programming Language :: Python :: 3.11
Classifier: Programming Language :: Python :: 3.12
Classifier: Programming Language :: Python :: 3.13
Classifier: Topic :: Scientific/Engineering :: Information Analysis
License-File: LICENSE
Requires-Dist: setuptools
Requires-Dist: scipy
Requires-Dist: numpy
Requires-Dist: pandas
Requires-Dist: matplotlib
Requires-Dist: numba
Requires-Dist: scikit-learn
Requires-Dist: imageio
Requires-Dist: tqdm
Provides-Extra: gstools
Requires-Dist: gstools>=1.3; extra == "gstools"
Dynamic: author
Dynamic: author-email
Dynamic: classifier
Dynamic: description
Dynamic: description-content-type
Dynamic: license
Dynamic: license-file
Dynamic: provides-extra
Dynamic: requires-dist
Dynamic: summary
